libgenerica/__init__.py
libgenerica/main.py
libgenerica/controller/__initi__.py
libgenerica/controller/endereco.py
libgenerica/controller/generic.py
libgenerica/controller/pessoa.py
libgenerica/model/__init__.py
libgenerica/model/dto.py
libgenerica/model/models.py
libgenerica/repository/__init__.py
libgenerica/repository/base.py
libgenerica/service/__init__.py
libgenerica/service/base.py
libgenerica/util/__init__.py
libgenerica/util/database.py
libgenerica-0.1.1.dist-info/METADATA
libgenerica-0.1.1.dist-info/WHEEL
libgenerica-0.1.1.dist-info/top_level.txt
libgenerica-0.1.1.dist-info/RECORD
