Metadata-Version: 2.4
Name: libgenerica
Version: 0.1.1
Summary: Biblioteca com CRUD genérico, models e utilitários
Author: Rafael
Requires-Python: >=3.10
Requires-Dist: fastapi
Requires-Dist: sqlmodel
Requires-Dist: sqlalchemy
Requires-Dist: uvicorn
